Nikos_Charalampous_9740/BaudController/design.sv
`timescale 1ns/1ps
module baud_controller (reset, clk, baud_select, sample_ENABLE);
  
  
  input clk, reset; 
  input [2:0] baud_select; 
  output reg sample_ENABLE;
  integer i=3;
  reg [31:0] sample;
  
  always @ (clk, reset, baud_select)
    begin
      
      
	  sample_ENABLE <= 0;
      if (reset)
        sample_ENABLE <= 0;
      else
      case (baud_select)
        3'b000 : sample <=  1041.667;
        3'b001 : sample <=  260.417;
        3'b010 : sample <=  65.104;
        3'b011 : sample <=  32.552;
        3'b100 : sample <=  16.276;
        3'b101 : sample <=  8.138;
        3'b110 : sample <=  5.425;
        3'b111 : sample <=  2.713;
        default : sample <= 0;
        endcase
        
    end
  
  always @ (clk)
    begin
      
   	 i <= i+1;
      if (i >= sample)
     begin
       sample_ENABLE <= 1;
       i <= 0;
     end
    end

endmodule

Nikos_Charalampous_9740/BaudController/testbench.sv
`timescale 1ns/1ps
module baud_controller_TB ();
  
  reg clk_TB;
  reg reset_TB;
  reg [2:0] baud_select_TB;
  wire sample_ENABLE_TB;
  
  baud_controller baud_controller_TB(reset_TB, clk_TB, baud_select_TB, sample_ENABLE_TB);
  
  initial begin 
    $dumpfile("dump.vcd"); $dumpvars;
    clk_TB=0; reset_TB=0; baud_select_TB=3'b111;
    #20 clk_TB = 1;
    #20 clk_TB = 0;
    #20 clk_TB = 1;
    #20 clk_TB = 0;
    #20 clk_TB = 1;
    #20 clk_TB = 0;
    #20 clk_TB = 1;
    #20 clk_TB = 0;
    
  end
  
endmodule

Nikos_Charalampous_9740/BaudController/dump.vcd
$date
	Mon Jan 30 19:43:55 2023
$end
$version
	Icarus Verilog
$end
$timescale
	1ps
$end
$scope module baud_controller_TB $end
$var wire 1 ! sample_ENABLE_TB $end
$var reg 3 " baud_select_TB [2:0] $end
$var reg 1 # clk_TB $end
$var reg 1 $ reset_TB $end
$scope module baud_controller_TB $end
$var wire 3 % baud_select [2:0] $end
$var wire 1 & clk $end
$var wire 1 ' reset $end
$var integer 32 ( i [31:0] $end
$var reg 32 ) sample [31:0] $end
$var reg 1 * sample_ENABLE $end
$upscope $end
$upscope $end
$enddefinitions $end
#0
$dumpvars
0*
b11 )
b100 (
0'
0&
b111 %
0$
0#
b111 "
0!
$end
#20000
1*
1!
b0 (
1#
1&
#40000
b1 (
0*
0!
0#
0&
#60000
b10 (
1#
1&
#80000
b11 (
0#
0&
#100000
1*
1!
b0 (
1#
1&
#120000
b1 (
0*
0!
0#
0&
#140000
b10 (
1#
1&
#160000
b11 (
0#
0&
